mkdocs_nav_enhancements/__init__.py
mkdocs_nav_enhancements-0.9.1.dist-info/LICENSE
mkdocs_nav_enhancements-0.9.1.dist-info/METADATA
mkdocs_nav_enhancements-0.9.1.dist-info/WHEEL
mkdocs_nav_enhancements-0.9.1.dist-info/entry_points.txt
mkdocs_nav_enhancements-0.9.1.dist-info/top_level.txt
mkdocs_nav_enhancements-0.9.1.dist-info/RECORD
