Metadata-Version: 2.1
Name: mkdocs-nav-enhancements
Version: 0.9.1
Summary: This is a small plugin for the excellent MkDocs project which makes some enhancements to the navigation.
Home-page: https://github.com/rylon/mkdocs-nav-enhancements
Author: Ryan Conway
Author-email: ryan@rjc.cc
License: MIT
Platform: UNKNOWN
Classifier: Programming Language :: Python :: 2
Classifier: Programming Language :: Python :: 3
Classifier: License :: OSI Approved :: MIT License
Classifier: Operating System :: OS Independent
Classifier: Intended Audience :: Developers
Classifier: Topic :: Documentation
Requires-Dist: mkdocs (>=1)
